odoo/addons/l10n_be_vat_reports/README.rst
odoo/addons/l10n_be_vat_reports/__init__.py
odoo/addons/l10n_be_vat_reports/__manifest__.py
odoo/addons/l10n_be_vat_reports/l10n_be_reports.xml
odoo/addons/l10n_be_vat_reports/i18n/l10n_be_vat_reports.pot
odoo/addons/l10n_be_vat_reports/readme/CONTRIBUTORS.rst
odoo/addons/l10n_be_vat_reports/readme/DESCRIPTION.rst
odoo/addons/l10n_be_vat_reports/static/description/icon.png
odoo/addons/l10n_be_vat_reports/static/description/index.html
odoo/addons/l10n_be_vat_reports/tests/__init__.py
odoo/addons/l10n_be_vat_reports/tests/common.py
odoo/addons/l10n_be_vat_reports/tests/test_vat_intra.py
odoo/addons/l10n_be_vat_reports/tests/test_vat_reports.py
odoo/addons/l10n_be_vat_reports/views/report_vatintraprint.xml
odoo/addons/l10n_be_vat_reports/views/report_vatpartnerlisting.xml
odoo/addons/l10n_be_vat_reports/wizard/__init__.py
odoo/addons/l10n_be_vat_reports/wizard/l10n_be_partner_vat_listing.py
odoo/addons/l10n_be_vat_reports/wizard/l10n_be_partner_vat_listing.xml
odoo/addons/l10n_be_vat_reports/wizard/l10n_be_vat_intra.py
odoo/addons/l10n_be_vat_reports/wizard/l10n_be_vat_intra_view.xml
odoo11_addon_l10n_be_vat_reports-11.0.1.0.2.dist-info/METADATA
odoo11_addon_l10n_be_vat_reports-11.0.1.0.2.dist-info/WHEEL
odoo11_addon_l10n_be_vat_reports-11.0.1.0.2.dist-info/top_level.txt
odoo11_addon_l10n_be_vat_reports-11.0.1.0.2.dist-info/RECORD
